pyqrlew-0.9.27.dist-info/METADATA
pyqrlew-0.9.27.dist-info/WHEEL
pyqrlew-0.9.27.dist-info/licenses/LICENSE
pyqrlew/io/postgresql.py
pyqrlew/io/__init__.py
pyqrlew/io/sqlite.py
pyqrlew/io/utils.py
pyqrlew/__init__.py
pyqrlew/pyqrlew.pyi
pyqrlew/utils.py
pyqrlew/wrappers.py
pyqrlew/py.typed
pyqrlew/tester/tester.py
pyqrlew/tester/__init__.py
pyqrlew/tester/stochatic_dataset.py
pyqrlew/tester/utils.py
pyqrlew/typing.py
pyqrlew/pyqrlew.abi3.so
pyqrlew-0.9.27.dist-info/RECORD
