Metadata-Version: 2.4
Name: pyqrlew
Version: 0.9.27
Classifier: Operating System :: OS Independent
Classifier: Programming Language :: Rust
Classifier: Programming Language :: Python
Classifier: Programming Language :: Python :: 3
Classifier: Programming Language :: Python :: 3 :: Only
Classifier: Programming Language :: Python :: 3.9
Classifier: Programming Language :: Python :: 3.10
Classifier: Programming Language :: Python :: 3.11
Classifier: Programming Language :: Python :: Implementation :: CPython
Classifier: Programming Language :: Python :: Implementation :: PyPy
Classifier: Topic :: Scientific/Engineering
Requires-Dist: sqlalchemy ~=2.0
Requires-Dist: psycopg2 <3.0
Requires-Dist: pymysql ~=1.0
Requires-Dist: qrlew-datasets ~=0.9
Requires-Dist: pandas >=1.4
Requires-Dist: numpy ~=1.24
Requires-Dist: pytest ~=7.0 ; extra == 'test'
Requires-Dist: mypy ~=1.0 ; extra == 'test'
Requires-Dist: graphviz ; extra == 'test'
Provides-Extra: test
License-File: LICENSE
Summary: A library to manipulate SQL queries, designed with privacy application in mind.
Keywords: SQL,Privecy,Differential Privacy,AST,Intermediate Representation,Rust
Author-email: Nicolas Grislain <ng@sarus.tech>
Requires-Python: >=3.9
Project-URL: homepage, https://qrlew.github.io
Project-URL: documentation, https://pyqrlew.readthedocs.io
Project-URL: repository, https://github.com/Qrlew/pyqrlew
Project-URL: changelog, https://github.com/me/spam/blob/master/CHANGELOG.md
